MANIFEST.in
README.md
setup.py
workfront_bridge/__init__.py
workfront_bridge/exceptions.py
workfront_bridge.egg-info/PKG-INFO
workfront_bridge.egg-info/SOURCES.txt
workfront_bridge.egg-info/dependency_links.txt
workfront_bridge.egg-info/not-zip-safe
workfront_bridge.egg-info/requires.txt
workfront_bridge.egg-info/top_level.txt
workfront_bridge/blocks/__init__.py
workfront_bridge/blocks/base.py
workfront_bridge/blocks/email.py
workfront_bridge/blocks/data/__init__.py
workfront_bridge/blocks/data/match_and_export.py
workfront_bridge/projects/__init__.py
workfront_bridge/projects/email.py
workfront_bridge/projects/email_builder.py
workfront_bridge/projects/match_and_export.py
workfront_bridge/projects/match_and_export_builder.py