Metadata-Version: 1.0
Name: workfront-bridge
Version: 0.1
Summary: Workfront Bridge Project Library for Python
Home-page: https://github.com/BridgeMarketing/workfront-bridge
Author: Bridge
Author-email: info@bridgecorp.com
License: bridgecorp
Platform: UNKNOWN
